fzstats/__init__.py
fzstats/main.py
fzstats-0.1.2.dist-info/LICENSE
fzstats-0.1.2.dist-info/METADATA
fzstats-0.1.2.dist-info/WHEEL
fzstats-0.1.2.dist-info/entry_points.txt
fzstats-0.1.2.dist-info/RECORD
