Metadata-Version: 2.1
Name: fzstats
Version: 0.1.2
Summary: Display statistics for file and folder sizes
Author: Mingfeng Yu
Author-email: mfdevworld@gmail.com
Requires-Python: >=3.8,<4.0
Classifier: Programming Language :: Python :: 3
Classifier: Programming Language :: Python :: 3.8
Classifier: Programming Language :: Python :: 3.9
Classifier: Programming Language :: Python :: 3.10
Classifier: Programming Language :: Python :: 3.11
Classifier: Programming Language :: Python :: 3.12
Requires-Dist: typer[all] (>=0.9.0,<0.10.0)
